torch_image2vector/__init__.py
torch_image2vector/data.py
torch_image2vector/image2vector.py
torch_image2vector/test_image2vector.py
torch_image2vector-1.0.0.dist-info/LICENSE
torch_image2vector-1.0.0.dist-info/METADATA
torch_image2vector-1.0.0.dist-info/WHEEL
torch_image2vector-1.0.0.dist-info/top_level.txt
torch_image2vector-1.0.0.dist-info/RECORD
