Metadata-Version: 2.1
Name: torch-image2vector
Version: 1.0.0
Summary: Extract images embeddings with variation of pre-trained torch models
Home-page: https://github.com/MajewskiLukasz/torch_image2vector
Author: lukasz-majewski
License: UNKNOWN
Platform: UNKNOWN
Classifier: Programming Language :: Python :: 3.7
Classifier: License :: OSI Approved :: MIT License
Classifier: Operating System :: OS Independent
Requires-Python: >=3.7
Requires-Dist: torch
Requires-Dist: torchvision
Requires-Dist: numpy >=1.23.0
Requires-Dist: Pillow >=9.1.1
